azure/mgmt/dellstorage/__init__.py
azure/mgmt/dellstorage/_client.py
azure/mgmt/dellstorage/_configuration.py
azure/mgmt/dellstorage/_patch.py
azure/mgmt/dellstorage/_version.py
azure/mgmt/dellstorage/py.typed
azure/mgmt/dellstorage/_utils/__init__.py
azure/mgmt/dellstorage/_utils/model_base.py
azure/mgmt/dellstorage/_utils/serialization.py
azure/mgmt/dellstorage/aio/__init__.py
azure/mgmt/dellstorage/aio/_client.py
azure/mgmt/dellstorage/aio/_configuration.py
azure/mgmt/dellstorage/aio/_patch.py
azure/mgmt/dellstorage/aio/operations/__init__.py
azure/mgmt/dellstorage/aio/operations/_operations.py
azure/mgmt/dellstorage/aio/operations/_patch.py
azure/mgmt/dellstorage/models/__init__.py
azure/mgmt/dellstorage/models/_enums.py
azure/mgmt/dellstorage/models/_models.py
azure/mgmt/dellstorage/models/_patch.py
azure/mgmt/dellstorage/operations/__init__.py
azure/mgmt/dellstorage/operations/_operations.py
azure/mgmt/dellstorage/operations/_patch.py
azure_mgmt_dellstorage-1.0.0.dist-info/licenses/LICENSE
azure_mgmt_dellstorage-1.0.0.dist-info/METADATA
azure_mgmt_dellstorage-1.0.0.dist-info/WHEEL
azure_mgmt_dellstorage-1.0.0.dist-info/top_level.txt
azure_mgmt_dellstorage-1.0.0.dist-info/RECORD
